dieStruct/__init__.py
dieStruct/dieStruct/__init__.py
dieStruct/dieStruct/analisis_sismico/__init__.py
dieStruct/dieStruct/analisis_sismico/ELF/__init__.py
dieStruct/dieStruct/analisis_sismico/ELF/f_asignar_propiedades.py
dieStruct/dieStruct/analisis_sismico/ELF/f_desplazamientos.py
dieStruct/dieStruct/analisis_sismico/ELF/f_diafragma_rigido.py
dieStruct/dieStruct/analisis_sismico/ELF/f_fuerzas_laterales_equivalentes.py
dieStruct/dieStruct/analisis_sismico/ELF/f_gdl_efectivos.py
dieStruct/dieStruct/analisis_sismico/ELF/f_gdl_totales.py
dieStruct/dieStruct/analisis_sismico/ELF/f_geometria.py
dieStruct/dieStruct/analisis_sismico/ELF/f_grafico_estructura.py
dieStruct/dieStruct/analisis_sismico/ELF/f_graficos.py
dieStruct/dieStruct/analisis_sismico/ELF/f_grid.py
dieStruct/dieStruct/analisis_sismico/ELF/f_mallado.py
dieStruct/dieStruct/analisis_sismico/ELF/f_mef.py
dieStruct/dieStruct/analisis_sismico/ELF/f_mostrar_tabla.py
dieStruct/dieStruct/analisis_sismico/ELF/f_periodos_estructura.py
dieStruct/dieStruct/analisis_sismico/ELF/f_peso_estructura.py
dieStruct/dieStruct/analisis_sismico/ELF/f_peso_reactivo.py
dieStruct/dieStruct/analisis_sismico/ELF/f_propiedades_elementos.py
dieStruct/dieStruct/analisis_sismico/ELF/f_restricciones.py
dieStruct-1.1.2.dist-info/LICENSE
dieStruct-1.1.2.dist-info/METADATA
dieStruct-1.1.2.dist-info/WHEEL
dieStruct-1.1.2.dist-info/top_level.txt
dieStruct-1.1.2.dist-info/RECORD
