Metadata-Version: 2.1
Name: dieStruct
Version: 1.1.2
Summary: Librería para comprender el analísis y diseño estructural
Home-page: https://www.youtube.com/results?search_query=daningenio
Author: Daniel Ilbay Yupa
Author-email: daningenio@gmail.com
Classifier: Environment :: Console
Classifier: Intended Audience :: Education
Classifier: License :: OSI Approved :: GNU General Public License v3 (GPLv3)
Classifier: Operating System :: OS Independent
Classifier: Programming Language :: Python
Classifier: Programming Language :: Python :: 3.8
Classifier: Topic :: Education
License-File: LICENSE
